HISTORY.rst
LICENSE
MANIFEST.in
README.rst
setup.cfg
setup.py
django_unsubscribe.egg-info/PKG-INFO
django_unsubscribe.egg-info/SOURCES.txt
django_unsubscribe.egg-info/dependency_links.txt
django_unsubscribe.egg-info/not-zip-safe
django_unsubscribe.egg-info/top_level.txt
unsubscribe/__init__.py
unsubscribe/compat.py
unsubscribe/mail.py
unsubscribe/models.py
unsubscribe/signals.py
unsubscribe/urls.py
unsubscribe/utils.py
unsubscribe/views.py
unsubscribe/runtests/__init__.py
unsubscribe/runtests/runtests.py
unsubscribe/runtests/settings.py
unsubscribe/runtests/urls.py
unsubscribe/templates/unsubscribe/unsubscribe.html
unsubscribe/tests/__init__.py
unsubscribe/tests/models.py
unsubscribe/tests/test_core.py
unsubscribe/tests/test_utils.py
unsubscribe/tests/tests.py