Metadata-Version: 1.1
Name: django-unsubscribe
Version: 0.1.2
Summary: Add unsubscribe link to your emails painlessly.
Home-page: https://github.com/theskumar/django-unsubscribe
Author: Saurabh Kumar
Author-email: me+github@saurabh-kumar.com
License: UNKNOWN
Keywords: email,django,unsubscribe
Platform: UNKNOWN
Classifier: Development Status :: 4 - Beta
Classifier: Programming Language :: Python
Classifier: Programming Language :: Python :: 2
Classifier: Programming Language :: Python :: 2.6
Classifier: Programming Language :: Python :: 2.7
Classifier: Programming Language :: Python :: 3
Classifier: Intended Audience :: Developers
Classifier: License :: OSI Approved :: BSD License
Classifier: Operating System :: OS Independent
Classifier: Topic :: Utilities
Classifier: Environment :: Web Environment
Classifier: Framework :: Django
